{"name":"Sort vaccination bookings by time","id":"manage-vaccination-bookings;sort-vaccination-bookings-by-time","testSteps":[{"number":1,"description":"Given I am on landing page","duration":3268,"startTime":"2022-12-19T12:57:45.434209300+07:00[Asia/Bangkok]","screenshots":[{"screenshot":"8058bdc50a44bd821dbcfa16ccaf81d174bd07fca027672a282ca177487ac2f1.png","timeStamp":1671429468703}],"result":"SUCCESS","precondition":false,"level":0},{"number":2,"description":"And I have logged in","duration":801,"startTime":"2022-12-19T12:57:48.706093300+07:00[Asia/Bangkok]","screenshots":[{"screenshot":"8eb16cbe3bd1b71060950c3115ae5a1b63cc3c13b563f46b93a8b74e6bb8a6e3.png","timeStamp":1671429469507}],"result":"SUCCESS","precondition":false,"level":0},{"number":3,"description":"When I go to Book Vaksinasi page","duration":638,"startTime":"2022-12-19T12:57:49.511938+07:00[Asia/Bangkok]","screenshots":[{"screenshot":"016e9e18bef710e40f961ea1596b1b9a818fabc1a92972192d8b37b181cd213c.png","timeStamp":1671429470150}],"result":"SUCCESS","precondition":false,"level":0},{"number":4,"description":"And I click the dots on the top right of page","duration":7,"startTime":"2022-12-19T12:57:50.152346100+07:00[Asia/Bangkok]","screenshots":[{"screenshot":"016e9e18bef710e40f961ea1596b1b9a818fabc1a92972192d8b37b181cd213c.png","timeStamp":1671429470160}],"result":"SUCCESS","precondition":false,"level":0},{"number":5,"description":"And I click Waktu button","duration":10,"startTime":"2022-12-19T12:57:50.160324800+07:00[Asia/Bangkok]","screenshots":[{"screenshot":"016e9e18bef710e40f961ea1596b1b9a818fabc1a92972192d8b37b181cd213c.png","timeStamp":1671429470171}],"result":"SUCCESS","precondition":false,"level":0},{"number":6,"description":"And I select time","duration":195,"startTime":"2022-12-19T12:57:50.176307600+07:00[Asia/Bangkok]","screenshots":[{"screenshot":"cadfa7a64320374cee6338792577f953c037bf2ca79fa15080f5760153f84d82.png","timeStamp":1671429470371}],"result":"SUCCESS","precondition":false,"level":0},{"number":7,"description":"Then bookings will be sorted by time","duration":12,"startTime":"2022-12-19T12:57:50.374751500+07:00[Asia/Bangkok]","screenshots":[{"screenshot":"cadfa7a64320374cee6338792577f953c037bf2ca79fa15080f5760153f84d82.png","timeStamp":1671429470387}],"result":"SUCCESS","precondition":false,"level":0}],"userStory":{"id":"manage-vaccination-bookings","storyName":"Manage vaccination bookings","displayName":"Manage vaccination bookings","path":"ManageVaccinationBookings.feature","narrative":"  As an admin\n  I want to manage vaccination bookings\n  So that I can approve or reject vaccination booking requests","type":"feature"},"featureTag":{"name":"Manage vaccination bookings","type":"feature","displayName":"Manage vaccination bookings"},"title":"Sort vaccination bookings by time","description":"","tags":[{"name":"Manage vaccination bookings","type":"feature","displayName":"Manage vaccination bookings"}],"startTime":"2022-12-19T12:57:45.416258+07:00[Asia/Bangkok]","duration":4972,"projectKey":"","sessionId":"0d5a2baa2a76a9c83b704a0dba6f36c6","driver":"chrome","isManualTestingUpToDate":false,"manual":false,"testSource":"Cucumber","result":"SUCCESS"}